scalegp/__init__.py
scalegp/_base_client.py
scalegp/_client.py
scalegp/_compat.py
scalegp/_constants.py
scalegp/_exceptions.py
scalegp/_files.py
scalegp/_models.py
scalegp/_qs.py
scalegp/_resource.py
scalegp/_response.py
scalegp/_streaming.py
scalegp/_types.py
scalegp/_version.py
scalegp/py.typed
scalegp/_utils/__init__.py
scalegp/_utils/_logs.py
scalegp/_utils/_proxy.py
scalegp/_utils/_reflection.py
scalegp/_utils/_streams.py
scalegp/_utils/_sync.py
scalegp/_utils/_transform.py
scalegp/_utils/_typing.py
scalegp/_utils/_utils.py
scalegp/lib/.keep
scalegp/resources/__init__.py
scalegp/resources/accounts.py
scalegp/resources/agents.py
scalegp/resources/application_deployments.py
scalegp/resources/application_schemas.py
scalegp/resources/application_specs.py
scalegp/resources/application_test_case_outputs.py
scalegp/resources/application_variant_reports.py
scalegp/resources/application_variants.py
scalegp/resources/chat_completions.py
scalegp/resources/chunks.py
scalegp/resources/completions.py
scalegp/resources/evaluation_configs.py
scalegp/resources/knowledge_base_data_sources.py
scalegp/resources/model_templates.py
scalegp/resources/question_sets.py
scalegp/resources/questions.py
scalegp/resources/studio_projects.py
scalegp/resources/themes.py
scalegp/resources/users.py
scalegp/resources/applications/__init__.py
scalegp/resources/applications/applications.py
scalegp/resources/applications/dashboards.py
scalegp/resources/applications/interactions/__init__.py
scalegp/resources/applications/interactions/interactions.py
scalegp/resources/applications/interactions/spans.py
scalegp/resources/applications/variant/__init__.py
scalegp/resources/applications/variant/threads.py
scalegp/resources/applications/variant/variant.py
scalegp/resources/evaluation_datasets/__init__.py
scalegp/resources/evaluation_datasets/autogenerated_draft_test_cases.py
scalegp/resources/evaluation_datasets/evaluation_dataset_versions.py
scalegp/resources/evaluation_datasets/evaluation_datasets.py
scalegp-0.1.0a10.dist-info/METADATA
scalegp-0.1.0a10.dist-info/WHEEL
scalegp-0.1.0a10.dist-info/licenses/LICENSE
scalegp-0.1.0a10.dist-info/RECORD
